meshagent/otel/__init__.py
meshagent/otel/version.py
meshagent_otel-0.25.1.dist-info/METADATA
meshagent_otel-0.25.1.dist-info/WHEEL
meshagent_otel-0.25.1.dist-info/top_level.txt
meshagent_otel-0.25.1.dist-info/RECORD
