Metadata-Version: 2.4
Name: meshagent-otel
Version: 0.25.1
Summary: CLI for Meshagent
License-Expression: Apache-2.0
Project-URL: Documentation, https://docs.meshagent.com
Project-URL: Website, https://www.meshagent.com
Project-URL: Source, https://www.meshagent.com
Requires-Python: >=3.13
Requires-Dist: opentelemetry-distro~=0.59b0
Requires-Dist: opentelemetry-exporter-otlp-proto-http~=1.33
